<?xml version="1.0" encoding="UTF-8"?>
<tileset version="1.5" tiledversion="1.7.2" name="map_tiles" tilewidth="48" tileheight="48" tilecount="900" columns="30">
    <image source="../images/map_tiles.png" width="1440" height="1440"/>
    <tile id="0">
        <properties>
            <property name="transparent" type="bool" value="true"/>
            <property name="walkable" type="bool" value="true"/>
        </properties>
    </tile>
    <tile id="1">
        <properties>
            <property name="transparent" type="bool" value="false"/>
            <property name="walkable" type="bool" value="false"/>
        </properties>
    </tile>
    <tile id="2">
        <properties>
            <property name="transparent" type="bool" value="true"/>
            <property name="walkable" type="bool" value="true"/>
        </properties>
    </tile>
    <tile id="3">
        <properties>
            <property name="transparent" type="bool" value="true"/>
   <property name="walkable" type="bool" value="true"/>
  </properties>
 </tile>
 <tile id="4">
  <properties>
   <property name="transparent" type="bool" value="true"/>
   <property name="walkable" type="bool" value="true"/>
  </properties>
 </tile>
 <tile id="5">
  <properties>
   <property name="transparent" type="bool" value="true"/>
   <property name="walkable" type="bool" value="true"/>
  </properties>
 </tile>
</tileset>
